titanic_model_ashmanova_startzev/VERSION
titanic_model_ashmanova_startzev/__init__.py
titanic_model_ashmanova_startzev/config.yml
titanic_model_ashmanova_startzev/pipeline.py
titanic_model_ashmanova_startzev/predict.py
titanic_model_ashmanova_startzev/train_pipeline.py
titanic_model_ashmanova_startzev/евуцачл.py
titanic_model_ashmanova_startzev/config/__init__.py
titanic_model_ashmanova_startzev/config/core.py
titanic_model_ashmanova_startzev/datasets/test.csv
titanic_model_ashmanova_startzev/datasets/train.csv
titanic_model_ashmanova_startzev/processing/__init__.py
titanic_model_ashmanova_startzev/processing/data_manager.py
titanic_model_ashmanova_startzev/processing/features.py
titanic_model_ashmanova_startzev/processing/validation.py
titanic_model_ashmanova_startzev/trained_models/titanic_model_output_v0.0.6.pkl
titanic_model_ashmanova_startzev-0.0.6.dist-info/METADATA
titanic_model_ashmanova_startzev-0.0.6.dist-info/WHEEL
titanic_model_ashmanova_startzev-0.0.6.dist-info/top_level.txt
titanic_model_ashmanova_startzev-0.0.6.dist-info/RECORD
