Metadata-Version: 2.4
Name: titanic_model_ashmanova_startzev
Version: 0.0.6
Summary: My package description
Home-page: https://github.com/Emilien-mipt/titanic-package
Author: Ekaterina Ashmanova and Stepan Startzev
Author-email: Ekaterina Ashmanova <m2005713@edu.misis.ru>, Stepan Startzev <m2401133@edu.misis.ru>
License: MIT
Requires-Python: >=3.6.0
Requires-Dist: feature-engine>=1.0.2
Requires-Dist: joblib>=1.0.1
Requires-Dist: numpy>=1.20.0
Requires-Dist: pandas>=1.2.0
Requires-Dist: pydantic>=1.8.1
Requires-Dist: ruamel.yaml==0.16.12
Requires-Dist: scikit-learn>=0.24.0
Requires-Dist: strictyaml>=1.3.2
Provides-Extra: test
Requires-Dist: black>=20.8b1; extra == "test"
Requires-Dist: flake8<3.10.0,>=3.9.0; extra == "test"
Requires-Dist: isort>=5.8.0; extra == "test"
Requires-Dist: mypy>=0.812; extra == "test"
Requires-Dist: pytest>=6.2.3; extra == "test"
Dynamic: author
Dynamic: home-page
Dynamic: requires-python
